{
  "2": {
    "k": 2,
    "N_sect": 21,
    "n_params": 882,
    "n_opt": 4000,
    "n_test": 1000,
    "resample_every": null,
    "pools_used": 1,
    "n_steps": 80,
    "n_steps_run": 39,
    "early_stopped": true,
    "sigma_baseline": 0.6360860268687245,
    "sigma_final": 0.08066675594376986,
    "reduction": 7.885355242401456,
    "train_sigma_final": 0.08066675594376986,
    "test_sigma_init": 0.5892113514528315,
    "test_sigma_final": 0.09110729210347177,
    "test_sigma_best": 0.09104845656616666,
    "best_step": 8,
    "overfit_ratio_final": 1.1294279909679232,
    "overfit_ratio_best": 1.1286986256102023,
    "time_s": 405.0,
    "history": [
      {
        "step": 0,
        "pool": 0,
        "train_sigma": 0.3475668664772993,
        "test_sigma": 0.34051128373369766,
        "gap": 0.9797000709097728,
        "time": 21.540120363235474
      },
      {
        "step": 1,
        "pool": 0,
        "train_sigma": 0.10380588910268713,
        "test_sigma": 0.10930914583558346,
        "gap": 1.0530148797960044,
        "time": 40.85601305961609
      },
      {
        "step": 2,
        "pool": 0,
        "train_sigma": 0.08787212888291296,
        "test_sigma": 0.09765153269540719,
        "gap": 1.1112913040439136,
        "time": 59.24137091636658
      },
      {
        "step": 3,
        "pool": 0,
        "train_sigma": 0.08362061172900474,
        "test_sigma": 0.09481016688065418,
        "gap": 1.1338133615658328,
        "time": 77.60546445846558
      },
      {
        "step": 4,
        "pool": 0,
        "train_sigma": 0.0820208109590593,
        "test_sigma": 0.09302525365422361,
        "gap": 1.1341664702712726,
        "time": 95.95317506790161
      },
      {
        "step": 5,
        "pool": 0,
        "train_sigma": 0.08131276410213428,
        "test_sigma": 0.09210469575774916,
        "gap": 1.132721249545268,
        "time": 114.45633006095886
      },
      {
        "step": 6,
        "pool": 0,
        "train_sigma": 0.0809651989020203,
        "test_sigma": 0.09137224525634631,
        "gap": 1.1285372789230106,
        "time": 133.1008586883545
      },
      {
        "step": 7,
        "pool": 0,
        "train_sigma": 0.0808255310573233,
        "test_sigma": 0.0913420221413552,
        "gap": 1.1301134795708718,
        "time": 151.57270550727844
      },
      {
        "step": 8,
        "pool": 0,
        "train_sigma": 0.08074093792940834,
        "test_sigma": 0.09104845656616666,
        "gap": 1.1276616162890027,
        "time": 170.02981662750244
      },
      {
        "step": 9,
        "pool": 0,
        "train_sigma": 0.0807050821821669,
        "test_sigma": 0.09111347080953172,
        "gap": 1.1289681931538225,
        "time": 188.51164412498474
      },
      {
        "step": 10,
        "pool": 0,
        "train_sigma": 0.08068741569550222,
        "test_sigma": 0.09114625001801442,
        "gap": 1.1296216297468455,
        "time": 206.99552512168884
      },
      {
        "step": 11,
        "pool": 0,
        "train_sigma": 0.08067765158344545,
        "test_sigma": 0.09115385558384013,
        "gap": 1.1298526146309438,
        "time": 225.55721044540405
      },
      {
        "step": 12,
        "pool": 0,
        "train_sigma": 0.08067226607740609,
        "test_sigma": 0.09112191209037221,
        "gap": 1.1295320749133233,
        "time": 244.19871497154236
      },
      {
        "step": 13,
        "pool": 0,
        "train_sigma": 0.08066954772228836,
        "test_sigma": 0.09107251339553689,
        "gap": 1.128957778579119,
        "time": 262.60787534713745
      },
      {
        "step": 14,
        "pool": 0,
        "train_sigma": 0.08066838533362515,
        "test_sigma": 0.09108221993410986,
        "gap": 1.1290943726890725,
        "time": 281.1072654724121
      },
      {
        "step": 15,
        "pool": 0,
        "train_sigma": 0.08066764444654756,
        "test_sigma": 0.09110280165288406,
        "gap": 1.1293598849691353,
        "time": 299.51140832901
      },
      {
        "step": 16,
        "pool": 0,
        "train_sigma": 0.08066723384695777,
        "test_sigma": 0.09110328266476901,
        "gap": 1.129371596373449,
        "time": 317.9552311897278
      },
      {
        "step": 17,
        "pool": 0,
        "train_sigma": 0.08066698517043247,
        "test_sigma": 0.0911179704833381,
        "gap": 1.1295571576255747,
        "time": 336.3858723640442
      },
      {
        "step": 18,
        "pool": 0,
        "train_sigma": 0.08066684174350093,
        "test_sigma": 0.09110846590433941,
        "gap": 1.1294413408924582,
        "time": 354.8193521499634
      },
      {
        "step": 19,
        "pool": 0,
        "train_sigma": 0.08066680336141624,
        "test_sigma": 0.09110918647028463,
        "gap": 1.129450810912672,
        "time": 362.12928891181946
      },
      {
        "step": 20,
        "pool": 0,
        "train_sigma": 0.08066679947154023,
        "test_sigma": 0.09110957882580342,
        "gap": 1.1294557292798937,
        "time": 364.99509477615356
      },
      {
        "step": 21,
        "pool": 0,
        "train_sigma": 0.0806667942846912,
        "test_sigma": 0.0911099891016867,
        "gap": 1.1294608879601578,
        "time": 367.83040857315063
      },
      {
        "step": 22,
        "pool": 0,
        "train_sigma": 0.08066677135357632,
        "test_sigma": 0.09111065771042097,
        "gap": 1.1294694975588808,
        "time": 372.89928460121155
      },
      {
        "step": 23,
        "pool": 0,
        "train_sigma": 0.08066676552702892,
        "test_sigma": 0.09111013676090944,
        "gap": 1.1294631210963983,
        "time": 375.73298931121826
      },
      {
        "step": 24,
        "pool": 0,
        "train_sigma": 0.08066676195816568,
        "test_sigma": 0.09110947536863052,
        "gap": 1.1294549719980147,
        "time": 378.57682394981384
      },
      {
        "step": 25,
        "pool": 0,
        "train_sigma": 0.08066675912279388,
        "test_sigma": 0.09110929591142347,
        "gap": 1.129452787023879,
        "time": 381.42455983161926
      },
      {
        "step": 26,
        "pool": 0,
        "train_sigma": 0.08066675594376986,
        "test_sigma": 0.09110729210347177,
        "gap": 1.1294279909679232,
        "time": 384.3078112602234
      },
      {
        "step": 27,
        "pool": 0,
        "train_sigma": 0.08066675594376986,
        "test_sigma": 0.09110729210347177,
        "gap": 1.1294279909679232,
        "time": 386.07935333251953
      },
      {
        "step": 28,
        "pool": 0,
        "train_sigma": 0.08066675594376986,
        "test_sigma": 0.09110729210347177,
        "gap": 1.1294279909679232,
        "time": 387.79949951171875
      },
      {
        "step": 29,
        "pool": 0,
        "train_sigma": 0.08066675594376986,
        "test_sigma": 0.09110729210347177,
        "gap": 1.1294279909679232,
        "time": 389.5160803794861
      },
      {
        "step": 30,
        "pool": 0,
        "train_sigma": 0.08066675594376986,
        "test_sigma": 0.09110729210347177,
        "gap": 1.1294279909679232,
        "time": 391.23328709602356
      },
      {
        "step": 31,
        "pool": 0,
        "train_sigma": 0.08066675594376986,
        "test_sigma": 0.09110729210347177,
        "gap": 1.1294279909679232,
        "time": 392.9567382335663
      },
      {
        "step": 32,
        "pool": 0,
        "train_sigma": 0.08066675594376986,
        "test_sigma": 0.09110729210347177,
        "gap": 1.1294279909679232,
        "time": 394.6783285140991
      },
      {
        "step": 33,
        "pool": 0,
        "train_sigma": 0.08066675594376986,
        "test_sigma": 0.09110729210347177,
        "gap": 1.1294279909679232,
        "time": 396.40821504592896
      },
      {
        "step": 34,
        "pool": 0,
        "train_sigma": 0.08066675594376986,
        "test_sigma": 0.09110729210347177,
        "gap": 1.1294279909679232,
        "time": 398.130943775177
      },
      {
        "step": 35,
        "pool": 0,
        "train_sigma": 0.08066675594376986,
        "test_sigma": 0.09110729210347177,
        "gap": 1.1294279909679232,
        "time": 399.84843015670776
      },
      {
        "step": 36,
        "pool": 0,
        "train_sigma": 0.08066675594376986,
        "test_sigma": 0.09110729210347177,
        "gap": 1.1294279909679232,
        "time": 401.58315777778625
      },
      {
        "step": 37,
        "pool": 0,
        "train_sigma": 0.08066675594376986,
        "test_sigma": 0.09110729210347177,
        "gap": 1.1294279909679232,
        "time": 403.30185556411743
      },
      {
        "step": 38,
        "pool": 0,
        "train_sigma": 0.08066675594376986,
        "test_sigma": 0.09110729210347177,
        "gap": 1.1294279909679232,
        "time": 405.02458691596985
      }
    ]
  },
  "3": {
    "k": 3,
    "N_sect": 56,
    "n_params": 6272,
    "n_opt": 4000,
    "n_test": 1000,
    "resample_every": 8,
    "pools_used": 10,
    "n_steps": 80,
    "n_steps_run": 80,
    "early_stopped": false,
    "sigma_baseline": 0.6868447710577353,
    "sigma_final": 0.011652208258360358,
    "reduction": 58.945459592599555,
    "train_sigma_final": 0.011652208258360358,
    "test_sigma_init": 0.6617322748933633,
    "test_sigma_final": 0.02445685568206078,
    "test_sigma_best": 0.022588711962837536,
    "best_step": 65,
    "overfit_ratio_final": 2.098903069683225,
    "overfit_ratio_best": 1.938577775301118,
    "time_s": 3885.9,
    "history": [
      {
        "step": 0,
        "pool": 0,
        "train_sigma": 0.31676084998709697,
        "test_sigma": 0.31776564984644995,
        "gap": 1.0031721087356404,
        "time": 57.104864835739136
      },
      {
        "step": 1,
        "pool": 0,
        "train_sigma": 0.06306164030411474,
        "test_sigma": 0.07629032216861414,
        "gap": 1.2097738308217816,
        "time": 105.49067211151123
      },
      {
        "step": 2,
        "pool": 0,
        "train_sigma": 0.040404525938671436,
        "test_sigma": 0.05415929647055824,
        "gap": 1.3404264797652785,
        "time": 153.97899270057678
      },
      {
        "step": 3,
        "pool": 0,
        "train_sigma": 0.03169410659681781,
        "test_sigma": 0.04622319081450754,
        "gap": 1.4584159573423185,
        "time": 202.6607596874237
      },
      {
        "step": 4,
        "pool": 0,
        "train_sigma": 0.026425535684253355,
        "test_sigma": 0.04183395316293086,
        "gap": 1.5830881789033775,
        "time": 251.2041072845459
      },
      {
        "step": 5,
        "pool": 0,
        "train_sigma": 0.02340363411020497,
        "test_sigma": 0.040185212283156115,
        "gap": 1.7170500997378724,
        "time": 299.3327829837799
      },
      {
        "step": 6,
        "pool": 0,
        "train_sigma": 0.020825032102676954,
        "test_sigma": 0.038835417499412536,
        "gap": 1.8648431036233764,
        "time": 347.6359987258911
      },
      {
        "step": 7,
        "pool": 0,
        "train_sigma": 0.01908429003783533,
        "test_sigma": 0.03697996903355154,
        "gap": 1.9377178276078044,
        "time": 395.98940658569336
      },
      {
        "step": 8,
        "pool": 1,
        "train_sigma": 0.028582784884151835,
        "test_sigma": 0.03413780368786969,
        "gap": 1.1943484102837691,
        "time": 444.421404838562
      },
      {
        "step": 9,
        "pool": 1,
        "train_sigma": 0.02438197745962548,
        "test_sigma": 0.03322055233715357,
        "gap": 1.362504431486906,
        "time": 492.6597945690155
      },
      {
        "step": 10,
        "pool": 1,
        "train_sigma": 0.021672316457363196,
        "test_sigma": 0.03295765100571505,
        "gap": 1.5207258103006174,
        "time": 540.8888778686523
      },
      {
        "step": 11,
        "pool": 1,
        "train_sigma": 0.019772070562541603,
        "test_sigma": 0.03215945904902963,
        "gap": 1.6265094213226239,
        "time": 589.2088203430176
      },
      {
        "step": 12,
        "pool": 1,
        "train_sigma": 0.01843911801606183,
        "test_sigma": 0.03166495771316606,
        "gap": 1.7172707331003332,
        "time": 637.6004972457886
      },
      {
        "step": 13,
        "pool": 1,
        "train_sigma": 0.017254619441795533,
        "test_sigma": 0.03147201956921471,
        "gap": 1.823976453110327,
        "time": 685.8080105781555
      },
      {
        "step": 14,
        "pool": 1,
        "train_sigma": 0.016245387917008133,
        "test_sigma": 0.03163795743371964,
        "gap": 1.9475039682244972,
        "time": 734.0067133903503
      },
      {
        "step": 15,
        "pool": 1,
        "train_sigma": 0.01551343099379646,
        "test_sigma": 0.031350709240527,
        "gap": 2.0208752823964975,
        "time": 782.2027690410614
      },
      {
        "step": 16,
        "pool": 2,
        "train_sigma": 0.023540812759819483,
        "test_sigma": 0.030712755988522772,
        "gap": 1.304659966581302,
        "time": 830.8315815925598
      },
      {
        "step": 17,
        "pool": 2,
        "train_sigma": 0.020163271673911215,
        "test_sigma": 0.02965501139088329,
        "gap": 1.4707440275802668,
        "time": 879.2127153873444
      },
      {
        "step": 18,
        "pool": 2,
        "train_sigma": 0.01818637422893881,
        "test_sigma": 0.02916090998797248,
        "gap": 1.6034482531196677,
        "time": 927.513929605484
      },
      {
        "step": 19,
        "pool": 2,
        "train_sigma": 0.017019004794517727,
        "test_sigma": 0.02852102451324793,
        "gap": 1.6758338608868193,
        "time": 975.4827415943146
      },
      {
        "step": 20,
        "pool": 2,
        "train_sigma": 0.016042999470336296,
        "test_sigma": 0.02829670182988403,
        "gap": 1.763803700312088,
        "time": 1023.802042722702
      },
      {
        "step": 21,
        "pool": 2,
        "train_sigma": 0.015282537201183834,
        "test_sigma": 0.028002269069111515,
        "gap": 1.8323049831635527,
        "time": 1072.1940252780914
      },
      {
        "step": 22,
        "pool": 2,
        "train_sigma": 0.01455955049354352,
        "test_sigma": 0.02801517154477601,
        "gap": 1.9241783293515435,
        "time": 1120.4572412967682
      },
      {
        "step": 23,
        "pool": 2,
        "train_sigma": 0.013997054668543963,
        "test_sigma": 0.02803566076532149,
        "gap": 2.0029685836926068,
        "time": 1168.8671383857727
      },
      {
        "step": 24,
        "pool": 3,
        "train_sigma": 0.021913146207816404,
        "test_sigma": 0.02587419630968467,
        "gap": 1.1807613596104862,
        "time": 1217.3814470767975
      },
      {
        "step": 25,
        "pool": 3,
        "train_sigma": 0.018775191607654243,
        "test_sigma": 0.02600691673740241,
        "gap": 1.3851745047864092,
        "time": 1265.908259153366
      },
      {
        "step": 26,
        "pool": 3,
        "train_sigma": 0.016850090906971576,
        "test_sigma": 0.02583047407201125,
        "gap": 1.532957549880287,
        "time": 1314.2861876487732
      },
      {
        "step": 27,
        "pool": 3,
        "train_sigma": 0.0156960933891131,
        "test_sigma": 0.025660313933199494,
        "gap": 1.6348216907907565,
        "time": 1362.6478629112244
      },
      {
        "step": 28,
        "pool": 3,
        "train_sigma": 0.01468418703225276,
        "test_sigma": 0.025475940105478753,
        "gap": 1.7349234281423058,
        "time": 1410.8159782886505
      },
      {
        "step": 29,
        "pool": 3,
        "train_sigma": 0.013963915528061852,
        "test_sigma": 0.025573963065390715,
        "gap": 1.8314320946726825,
        "time": 1459.3199427127838
      },
      {
        "step": 30,
        "pool": 3,
        "train_sigma": 0.013358872638768733,
        "test_sigma": 0.025865278655346522,
        "gap": 1.93618723336601,
        "time": 1508.1946761608124
      },
      {
        "step": 31,
        "pool": 3,
        "train_sigma": 0.012879061700783501,
        "test_sigma": 0.025889989379254984,
        "gap": 2.010238787634658,
        "time": 1556.372938632965
      },
      {
        "step": 32,
        "pool": 4,
        "train_sigma": 0.020628270197282722,
        "test_sigma": 0.025189831382819262,
        "gap": 1.221131541419184,
        "time": 1604.5052053928375
      },
      {
        "step": 33,
        "pool": 4,
        "train_sigma": 0.017792446778457666,
        "test_sigma": 0.02561775695609401,
        "gap": 1.4398107958434865,
        "time": 1652.8541021347046
      },
      {
        "step": 34,
        "pool": 4,
        "train_sigma": 0.01629365286923024,
        "test_sigma": 0.02611986938946861,
        "gap": 1.603070201574915,
        "time": 1701.1244781017303
      },
      {
        "step": 35,
        "pool": 4,
        "train_sigma": 0.015409105160707296,
        "test_sigma": 0.025728467447810557,
        "gap": 1.669692508388955,
        "time": 1749.7456893920898
      },
      {
        "step": 36,
        "pool": 4,
        "train_sigma": 0.014510176543339897,
        "test_sigma": 0.025148507983495272,
        "gap": 1.7331634738130266,
        "time": 1801.5164575576782
      },
      {
        "step": 37,
        "pool": 4,
        "train_sigma": 0.013832050514224821,
        "test_sigma": 0.02542611455856126,
        "gap": 1.8382028414668636,
        "time": 1850.282548904419
      },
      {
        "step": 38,
        "pool": 4,
        "train_sigma": 0.013272853280053563,
        "test_sigma": 0.0256583826550843,
        "gap": 1.9331474637517243,
        "time": 1898.7245934009552
      },
      {
        "step": 39,
        "pool": 4,
        "train_sigma": 0.012766391029346546,
        "test_sigma": 0.02584256557314843,
        "gap": 2.02426555114466,
        "time": 1946.9250628948212
      },
      {
        "step": 40,
        "pool": 5,
        "train_sigma": 0.019791716713965422,
        "test_sigma": 0.025280197016977472,
        "gap": 1.2773119877539107,
        "time": 1995.5271019935608
      },
      {
        "step": 41,
        "pool": 5,
        "train_sigma": 0.01739372048336854,
        "test_sigma": 0.0248404818173557,
        "gap": 1.4281292976455253,
        "time": 2043.8649010658264
      },
      {
        "step": 42,
        "pool": 5,
        "train_sigma": 0.015991531424212772,
        "test_sigma": 0.02474053502811402,
        "gap": 1.5471022988238876,
        "time": 2092.0666992664337
      },
      {
        "step": 43,
        "pool": 5,
        "train_sigma": 0.015010508359063302,
        "test_sigma": 0.02485736314497806,
        "gap": 1.6559974219640108,
        "time": 2140.3644959926605
      },
      {
        "step": 44,
        "pool": 5,
        "train_sigma": 0.014225173400744962,
        "test_sigma": 0.025122148799515912,
        "gap": 1.7660346269100862,
        "time": 2189.1543843746185
      },
      {
        "step": 45,
        "pool": 5,
        "train_sigma": 0.01360492870921846,
        "test_sigma": 0.02525132413410702,
        "gap": 1.8560423706591838,
        "time": 2238.0981867313385
      },
      {
        "step": 46,
        "pool": 5,
        "train_sigma": 0.013039974795847129,
        "test_sigma": 0.025707583043823073,
        "gap": 1.9714442279451512,
        "time": 2286.2495210170746
      },
      {
        "step": 47,
        "pool": 5,
        "train_sigma": 0.012619216809214516,
        "test_sigma": 0.025747410102478732,
        "gap": 2.040333444756892,
        "time": 2334.681676864624
      },
      {
        "step": 48,
        "pool": 6,
        "train_sigma": 0.01880350793759108,
        "test_sigma": 0.024313546122199138,
        "gap": 1.2930324598418494,
        "time": 2383.7476828098297
      },
      {
        "step": 49,
        "pool": 6,
        "train_sigma": 0.016470690047085377,
        "test_sigma": 0.024632403774345585,
        "gap": 1.4955295560737292,
        "time": 2432.1329505443573
      },
      {
        "step": 50,
        "pool": 6,
        "train_sigma": 0.015032608100981497,
        "test_sigma": 0.024591991536332528,
        "gap": 1.6359098415348756,
        "time": 2480.3629796504974
      },
      {
        "step": 51,
        "pool": 6,
        "train_sigma": 0.014109514128728804,
        "test_sigma": 0.02457778353254415,
        "gap": 1.7419298289301535,
        "time": 2528.6906323432922
      },
      {
        "step": 52,
        "pool": 6,
        "train_sigma": 0.013443410562771398,
        "test_sigma": 0.024714640664723217,
        "gap": 1.8384204327706124,
        "time": 2577.0550713539124
      },
      {
        "step": 53,
        "pool": 6,
        "train_sigma": 0.012891016756362821,
        "test_sigma": 0.024821248617470273,
        "gap": 1.9254686489503523,
        "time": 2625.820015192032
      },
      {
        "step": 54,
        "pool": 6,
        "train_sigma": 0.012482167082772732,
        "test_sigma": 0.025326094337832027,
        "gap": 2.0289821607007523,
        "time": 2673.894729614258
      },
      {
        "step": 55,
        "pool": 6,
        "train_sigma": 0.01206781244859867,
        "test_sigma": 0.025710943803030257,
        "gap": 2.1305388953087223,
        "time": 2722.282023668289
      },
      {
        "step": 56,
        "pool": 7,
        "train_sigma": 0.019020061184081324,
        "test_sigma": 0.02350733908356267,
        "gap": 1.2359234208582321,
        "time": 2770.7853248119354
      },
      {
        "step": 57,
        "pool": 7,
        "train_sigma": 0.01670361715992118,
        "test_sigma": 0.02338439433340252,
        "gap": 1.399959907457126,
        "time": 2819.072284936905
      },
      {
        "step": 58,
        "pool": 7,
        "train_sigma": 0.015315928146760836,
        "test_sigma": 0.023148256201651108,
        "gap": 1.5113844867799755,
        "time": 2867.448119163513
      },
      {
        "step": 59,
        "pool": 7,
        "train_sigma": 0.014394258552865866,
        "test_sigma": 0.022987332492575962,
        "gap": 1.5969792683763648,
        "time": 2915.9421088695526
      },
      {
        "step": 60,
        "pool": 7,
        "train_sigma": 0.013756917057097312,
        "test_sigma": 0.022991842531714886,
        "gap": 1.6712932437034065,
        "time": 2964.5616796016693
      },
      {
        "step": 61,
        "pool": 7,
        "train_sigma": 0.01316926742229989,
        "test_sigma": 0.023100205605895312,
        "gap": 1.7540995155720724,
        "time": 3013.1670615673065
      },
      {
        "step": 62,
        "pool": 7,
        "train_sigma": 0.012730876639370073,
        "test_sigma": 0.02348500608069109,
        "gap": 1.8447281162134592,
        "time": 3062.0942299365997
      },
      {
        "step": 63,
        "pool": 7,
        "train_sigma": 0.01236562412306037,
        "test_sigma": 0.023748879473455435,
        "gap": 1.920556474716605,
        "time": 3110.727988243103
      },
      {
        "step": 64,
        "pool": 8,
        "train_sigma": 0.018080965312457255,
        "test_sigma": 0.023001733729874324,
        "gap": 1.2721518642606324,
        "time": 3159.339911222458
      },
      {
        "step": 65,
        "pool": 8,
        "train_sigma": 0.015814658835153893,
        "test_sigma": 0.022588711962837536,
        "gap": 1.4283401367233937,
        "time": 3208.0944032669067
      },
      {
        "step": 66,
        "pool": 8,
        "train_sigma": 0.014361473028185107,
        "test_sigma": 0.02279082697305792,
        "gap": 1.5869421561653032,
        "time": 3256.5642564296722
      },
      {
        "step": 67,
        "pool": 8,
        "train_sigma": 0.013567804433431028,
        "test_sigma": 0.02304946840273907,
        "gap": 1.6988355423184942,
        "time": 3304.9396216869354
      },
      {
        "step": 68,
        "pool": 8,
        "train_sigma": 0.012909234114886235,
        "test_sigma": 0.02326544101788067,
        "gap": 1.8022324803182719,
        "time": 3353.2254767417908
      },
      {
        "step": 69,
        "pool": 8,
        "train_sigma": 0.012395953835802411,
        "test_sigma": 0.023266869177204955,
        "gap": 1.876972880457557,
        "time": 3401.614644050598
      },
      {
        "step": 70,
        "pool": 8,
        "train_sigma": 0.011929785974230401,
        "test_sigma": 0.023894560354943382,
        "gap": 2.002932861206241,
        "time": 3449.9951531887054
      },
      {
        "step": 71,
        "pool": 8,
        "train_sigma": 0.011560213780336875,
        "test_sigma": 0.024316001650718545,
        "gap": 2.103421451606577,
        "time": 3498.2054674625397
      },
      {
        "step": 72,
        "pool": 9,
        "train_sigma": 0.01896018371369443,
        "test_sigma": 0.023665548660882364,
        "gap": 1.2481708520466168,
        "time": 3546.9485981464386
      },
      {
        "step": 73,
        "pool": 9,
        "train_sigma": 0.01644258770516485,
        "test_sigma": 0.023454190411384843,
        "gap": 1.4264293937150505,
        "time": 3595.8513600826263
      },
      {
        "step": 74,
        "pool": 9,
        "train_sigma": 0.014891182976195507,
        "test_sigma": 0.023113639172889233,
        "gap": 1.5521694421348418,
        "time": 3644.1044504642487
      },
      {
        "step": 75,
        "pool": 9,
        "train_sigma": 0.013893093469704368,
        "test_sigma": 0.023442442915581483,
        "gap": 1.6873450802516134,
        "time": 3692.4454686641693
      },
      {
        "step": 76,
        "pool": 9,
        "train_sigma": 0.013120925163422415,
        "test_sigma": 0.023317352506924266,
        "gap": 1.7771119198154357,
        "time": 3740.712385416031
      },
      {
        "step": 77,
        "pool": 9,
        "train_sigma": 0.012509102708007048,
        "test_sigma": 0.02364737945841835,
        "gap": 1.8904137259406877,
        "time": 3789.252133369446
      },
      {
        "step": 78,
        "pool": 9,
        "train_sigma": 0.012040328449085974,
        "test_sigma": 0.023944957817663697,
        "gap": 1.9887296197041406,
        "time": 3837.6385972499847
      },
      {
        "step": 79,
        "pool": 9,
        "train_sigma": 0.011652208258360358,
        "test_sigma": 0.02445685568206078,
        "gap": 2.098903069683225,
        "time": 3885.9445836544037
      }
    ]
  },
  "4": {
    "k": 4,
    "N_sect": 126,
    "n_params": 31752,
    "n_opt": 4000,
    "n_test": 1000,
    "resample_every": 8,
    "pools_used": 10,
    "n_steps": 80,
    "n_steps_run": 80,
    "early_stopped": false,
    "sigma_baseline": 0.7492048915224088,
    "sigma_final": 0.004560450255968779,
    "reduction": 164.2830969468068,
    "train_sigma_final": 0.004560450255968779,
    "test_sigma_init": 0.7879325077144019,
    "test_sigma_final": 0.01627463087815927,
    "test_sigma_best": 0.015335426312781411,
    "best_step": 73,
    "overfit_ratio_final": 3.5686456302990726,
    "overfit_ratio_best": 3.362700051976271,
    "time_s": 9096.0,
    "history": [
      {
        "step": 0,
        "pool": 0,
        "train_sigma": 0.42104840914890584,
        "test_sigma": 0.4427119255782955,
        "gap": 1.0514513674880748,
        "time": 130.1367347240448
      },
      {
        "step": 1,
        "pool": 0,
        "train_sigma": 0.2695026004479799,
        "test_sigma": 2.2626162001936354,
        "gap": 8.395526412111083,
        "time": 261.1112005710602
      },
      {
        "step": 2,
        "pool": 0,
        "train_sigma": 0.2606164111724009,
        "test_sigma": 0.33233191319488026,
        "gap": 1.2751764622184083,
        "time": 390.59357380867004
      },
      {
        "step": 3,
        "pool": 0,
        "train_sigma": 0.24946659619478706,
        "test_sigma": 0.30200831663001204,
        "gap": 1.2106162557900122,
        "time": 521.5066421031952
      },
      {
        "step": 4,
        "pool": 0,
        "train_sigma": 0.20142835548183355,
        "test_sigma": 0.22699878238693225,
        "gap": 1.1269455178936059,
        "time": 632.6962442398071
      },
      {
        "step": 5,
        "pool": 0,
        "train_sigma": 0.18735780119530185,
        "test_sigma": 2.230790812622668,
        "gap": 11.906580875686574,
        "time": 757.0339827537537
      },
      {
        "step": 6,
        "pool": 0,
        "train_sigma": 0.12569777207748317,
        "test_sigma": 2.226975085463554,
        "gap": 17.716901808655702,
        "time": 888.0759682655334
      },
      {
        "step": 7,
        "pool": 0,
        "train_sigma": 0.052650988457127755,
        "test_sigma": 0.08161013070970959,
        "gap": 1.5500208657271926,
        "time": 1011.808117389679
      },
      {
        "step": 8,
        "pool": 1,
        "train_sigma": 0.0414295182022794,
        "test_sigma": 0.060523344753795554,
        "gap": 1.4608749360369253,
        "time": 1129.8311369419098
      },
      {
        "step": 9,
        "pool": 1,
        "train_sigma": 0.0286569800519323,
        "test_sigma": 0.05096756707903563,
        "gap": 1.7785393641155485,
        "time": 1240.07040309906
      },
      {
        "step": 10,
        "pool": 1,
        "train_sigma": 0.021275781701462677,
        "test_sigma": 0.04619584207704194,
        "gap": 2.1712876511543664,
        "time": 1357.109355688095
      },
      {
        "step": 11,
        "pool": 1,
        "train_sigma": 0.01680141724868199,
        "test_sigma": 0.043159151756151565,
        "gap": 2.5687804259213456,
        "time": 1467.8329932689667
      },
      {
        "step": 12,
        "pool": 1,
        "train_sigma": 0.014321878549442297,
        "test_sigma": 0.04168240588416725,
        "gap": 2.9104007369054523,
        "time": 1578.126769542694
      },
      {
        "step": 13,
        "pool": 1,
        "train_sigma": 0.01217559154588306,
        "test_sigma": 0.040670601891079794,
        "gap": 3.3403388852044538,
        "time": 1688.5832438468933
      },
      {
        "step": 14,
        "pool": 1,
        "train_sigma": 0.010744419829913887,
        "test_sigma": 0.03962854634270769,
        "gap": 3.6882909426506743,
        "time": 1798.6759119033813
      },
      {
        "step": 15,
        "pool": 1,
        "train_sigma": 0.009569529021947711,
        "test_sigma": 0.0387093345483511,
        "gap": 4.045061617930334,
        "time": 1909.537612915039
      },
      {
        "step": 16,
        "pool": 2,
        "train_sigma": 0.02175045551817536,
        "test_sigma": 0.034075715738463935,
        "gap": 1.5666667629093656,
        "time": 2020.119999885559
      },
      {
        "step": 17,
        "pool": 2,
        "train_sigma": 0.01680446719447922,
        "test_sigma": 0.03267680695142965,
        "gap": 1.9445309734166982,
        "time": 2131.151344060898
      },
      {
        "step": 18,
        "pool": 2,
        "train_sigma": 0.013883363865759292,
        "test_sigma": 0.032090982292812605,
        "gap": 2.311470231790077,
        "time": 2242.0409486293793
      },
      {
        "step": 19,
        "pool": 2,
        "train_sigma": 0.011748460075778887,
        "test_sigma": 0.03139544968279311,
        "gap": 2.672303389575224,
        "time": 2352.8363976478577
      },
      {
        "step": 20,
        "pool": 2,
        "train_sigma": 0.010222029494350878,
        "test_sigma": 0.030328136175543766,
        "gap": 2.9669388248492496,
        "time": 2463.1789813041687
      },
      {
        "step": 21,
        "pool": 2,
        "train_sigma": 0.008838140736486876,
        "test_sigma": 0.02959161178032261,
        "gap": 3.3481715965619654,
        "time": 2573.376983642578
      },
      {
        "step": 22,
        "pool": 2,
        "train_sigma": 0.007865673612311514,
        "test_sigma": 0.029400045308337515,
        "gap": 3.737765734687994,
        "time": 2683.9670491218567
      },
      {
        "step": 23,
        "pool": 2,
        "train_sigma": 0.007135086313261999,
        "test_sigma": 0.029017654097555953,
        "gap": 4.066896015486285,
        "time": 2793.5924701690674
      },
      {
        "step": 24,
        "pool": 3,
        "train_sigma": 0.017912768402618774,
        "test_sigma": 0.02681901619799999,
        "gap": 1.4972010799893531,
        "time": 2903.901398897171
      },
      {
        "step": 25,
        "pool": 3,
        "train_sigma": 0.013636407876690007,
        "test_sigma": 0.026113248908463605,
        "gap": 1.9149653739165016,
        "time": 3014.926454782486
      },
      {
        "step": 26,
        "pool": 3,
        "train_sigma": 0.01144167103241161,
        "test_sigma": 0.025959198626400722,
        "gap": 2.268829312856864,
        "time": 3124.9771857261658
      },
      {
        "step": 27,
        "pool": 3,
        "train_sigma": 0.009919339964252415,
        "test_sigma": 0.0258505546978949,
        "gap": 2.6060760888381513,
        "time": 3234.8462524414062
      },
      {
        "step": 28,
        "pool": 3,
        "train_sigma": 0.008681857453295184,
        "test_sigma": 0.025774967117453324,
        "gap": 2.9688309507627864,
        "time": 3345.7186601161957
      },
      {
        "step": 29,
        "pool": 3,
        "train_sigma": 0.007660944955228926,
        "test_sigma": 0.026151899463927864,
        "gap": 3.4136649743290564,
        "time": 3456.081248521805
      },
      {
        "step": 30,
        "pool": 3,
        "train_sigma": 0.007047739040022883,
        "test_sigma": 0.02616256696141744,
        "gap": 3.712192919295788,
        "time": 3566.257495164871
      },
      {
        "step": 31,
        "pool": 3,
        "train_sigma": 0.006428895582121785,
        "test_sigma": 0.02585056960236266,
        "gap": 4.020996961632245,
        "time": 3676.4877309799194
      },
      {
        "step": 32,
        "pool": 4,
        "train_sigma": 0.015499295910356783,
        "test_sigma": 0.022717278216084467,
        "gap": 1.4656974321591316,
        "time": 3786.716744184494
      },
      {
        "step": 33,
        "pool": 4,
        "train_sigma": 0.011716859465208082,
        "test_sigma": 0.02168215088675622,
        "gap": 1.850508743502384,
        "time": 3897.2515580654144
      },
      {
        "step": 34,
        "pool": 4,
        "train_sigma": 0.009655849228669036,
        "test_sigma": 0.0215568303571748,
        "gap": 2.2325152191865985,
        "time": 4007.121201992035
      },
      {
        "step": 35,
        "pool": 4,
        "train_sigma": 0.008264103560634856,
        "test_sigma": 0.021633490133815887,
        "gap": 2.6177660982934223,
        "time": 4117.252494812012
      },
      {
        "step": 36,
        "pool": 4,
        "train_sigma": 0.007311017821804287,
        "test_sigma": 0.021656754630126923,
        "gap": 2.9622078837693557,
        "time": 4228.248485803604
      },
      {
        "step": 37,
        "pool": 4,
        "train_sigma": 0.0066053384115466116,
        "test_sigma": 0.021819145911394538,
        "gap": 3.3032593565914934,
        "time": 4338.909112930298
      },
      {
        "step": 38,
        "pool": 4,
        "train_sigma": 0.006012717761008496,
        "test_sigma": 0.02210537543062528,
        "gap": 3.676436564838461,
        "time": 4449.757757663727
      },
      {
        "step": 39,
        "pool": 4,
        "train_sigma": 0.00554338282356924,
        "test_sigma": 0.02228435230561573,
        "gap": 4.019991585439055,
        "time": 4560.613622665405
      },
      {
        "step": 40,
        "pool": 5,
        "train_sigma": 0.014440861941784785,
        "test_sigma": 0.022589426074642434,
        "gap": 1.5642713132849566,
        "time": 4671.951825141907
      },
      {
        "step": 41,
        "pool": 5,
        "train_sigma": 0.01078665608577168,
        "test_sigma": 0.02262981026926362,
        "gap": 2.097944913541264,
        "time": 4783.040407180786
      },
      {
        "step": 42,
        "pool": 5,
        "train_sigma": 0.008966745103131014,
        "test_sigma": 0.022595883487930516,
        "gap": 2.5199649625414766,
        "time": 4896.180061101913
      },
      {
        "step": 43,
        "pool": 5,
        "train_sigma": 0.00785922865690706,
        "test_sigma": 0.022809146728197314,
        "gap": 2.902211873954267,
        "time": 5009.559314250946
      },
      {
        "step": 44,
        "pool": 5,
        "train_sigma": 0.00700353047560007,
        "test_sigma": 0.023286366646522786,
        "gap": 3.324946857538674,
        "time": 5129.882646560669
      },
      {
        "step": 45,
        "pool": 5,
        "train_sigma": 0.0062372066711837496,
        "test_sigma": 0.02379706983960093,
        "gap": 3.81534092008603,
        "time": 5242.684504270554
      },
      {
        "step": 46,
        "pool": 5,
        "train_sigma": 0.005744053988565421,
        "test_sigma": 0.02391742834223543,
        "gap": 4.1638585552725305,
        "time": 5356.4355347156525
      },
      {
        "step": 47,
        "pool": 5,
        "train_sigma": 0.005339007814530939,
        "test_sigma": 0.024078148943818604,
        "gap": 4.509854598505397,
        "time": 5470.817709207535
      },
      {
        "step": 48,
        "pool": 6,
        "train_sigma": 0.013108049502840932,
        "test_sigma": 0.01929848209249911,
        "gap": 1.4722619172529456,
        "time": 5585.386251211166
      },
      {
        "step": 49,
        "pool": 6,
        "train_sigma": 0.010040958968146309,
        "test_sigma": 0.018550957871478077,
        "gap": 1.8475285010454359,
        "time": 5698.606038093567
      },
      {
        "step": 50,
        "pool": 6,
        "train_sigma": 0.008417249444000277,
        "test_sigma": 0.01809556160885233,
        "gap": 2.149818860572161,
        "time": 5811.462733745575
      },
      {
        "step": 51,
        "pool": 6,
        "train_sigma": 0.007340758892994362,
        "test_sigma": 0.017914286270729277,
        "gap": 2.440386141523561,
        "time": 5924.706040382385
      },
      {
        "step": 52,
        "pool": 6,
        "train_sigma": 0.00646137739337347,
        "test_sigma": 0.017933626955405055,
        "gap": 2.775511452681446,
        "time": 6037.751869440079
      },
      {
        "step": 53,
        "pool": 6,
        "train_sigma": 0.0058599209321777215,
        "test_sigma": 0.01811004775516245,
        "gap": 3.0904935347706504,
        "time": 6150.668597459793
      },
      {
        "step": 54,
        "pool": 6,
        "train_sigma": 0.005284634968173483,
        "test_sigma": 0.018462891421565472,
        "gap": 3.493692853481375,
        "time": 6264.066450834274
      },
      {
        "step": 55,
        "pool": 6,
        "train_sigma": 0.004871444579878873,
        "test_sigma": 0.018646915614596672,
        "gap": 3.8278000106203245,
        "time": 6377.363638877869
      },
      {
        "step": 56,
        "pool": 7,
        "train_sigma": 0.012323818555492866,
        "test_sigma": 0.017349991943107414,
        "gap": 1.407842209375464,
        "time": 6491.2312297821045
      },
      {
        "step": 57,
        "pool": 7,
        "train_sigma": 0.009675051010029988,
        "test_sigma": 0.016892000418587523,
        "gap": 1.7459339905366729,
        "time": 6604.999036073685
      },
      {
        "step": 58,
        "pool": 7,
        "train_sigma": 0.008127713450099433,
        "test_sigma": 0.01705356718513345,
        "gap": 2.098199855326447,
        "time": 6718.560073137283
      },
      {
        "step": 59,
        "pool": 7,
        "train_sigma": 0.007171816696161681,
        "test_sigma": 0.017597080963120598,
        "gap": 2.4536434363330093,
        "time": 6831.576403617859
      },
      {
        "step": 60,
        "pool": 7,
        "train_sigma": 0.0064281432768474945,
        "test_sigma": 0.017621710503485617,
        "gap": 2.741337544070377,
        "time": 6945.482987880707
      },
      {
        "step": 61,
        "pool": 7,
        "train_sigma": 0.005776169093620185,
        "test_sigma": 0.017901787803782456,
        "gap": 3.0992492625527692,
        "time": 7058.012232065201
      },
      {
        "step": 62,
        "pool": 7,
        "train_sigma": 0.005303705939185967,
        "test_sigma": 0.018239489823608387,
        "gap": 3.4390085032519453,
        "time": 7170.345695257187
      },
      {
        "step": 63,
        "pool": 7,
        "train_sigma": 0.0048511719307248536,
        "test_sigma": 0.01838885406915335,
        "gap": 3.7906003604382086,
        "time": 7283.112926244736
      },
      {
        "step": 64,
        "pool": 8,
        "train_sigma": 0.011857919289330771,
        "test_sigma": 0.016847784071516582,
        "gap": 1.4208044143693463,
        "time": 7396.408952713013
      },
      {
        "step": 65,
        "pool": 8,
        "train_sigma": 0.00919918208385208,
        "test_sigma": 0.016815864073106278,
        "gap": 1.8279738263496548,
        "time": 7509.642694473267
      },
      {
        "step": 66,
        "pool": 8,
        "train_sigma": 0.007697825578574866,
        "test_sigma": 0.017154960455163824,
        "gap": 2.2285462667419647,
        "time": 7622.643581390381
      },
      {
        "step": 67,
        "pool": 8,
        "train_sigma": 0.0067386027499506725,
        "test_sigma": 0.017377166102947962,
        "gap": 2.5787491484158442,
        "time": 7736.705646753311
      },
      {
        "step": 68,
        "pool": 8,
        "train_sigma": 0.005994454045664117,
        "test_sigma": 0.01728815299776994,
        "gap": 2.8840246110944388,
        "time": 7849.439101219177
      },
      {
        "step": 69,
        "pool": 8,
        "train_sigma": 0.005493134403948239,
        "test_sigma": 0.017216426609912808,
        "gap": 3.1341717394605073,
        "time": 7962.454003095627
      },
      {
        "step": 70,
        "pool": 8,
        "train_sigma": 0.005062588249947927,
        "test_sigma": 0.01724962200256271,
        "gap": 3.4072733453565256,
        "time": 8075.34174990654
      },
      {
        "step": 71,
        "pool": 8,
        "train_sigma": 0.00466767380780341,
        "test_sigma": 0.01751393705840257,
        "gap": 3.752176732899115,
        "time": 8188.296949863434
      },
      {
        "step": 72,
        "pool": 9,
        "train_sigma": 0.011180037092571257,
        "test_sigma": 0.015720041049863888,
        "gap": 1.4060812964841864,
        "time": 8301.959515810013
      },
      {
        "step": 73,
        "pool": 9,
        "train_sigma": 0.008837921969810352,
        "test_sigma": 0.015335426312781411,
        "gap": 1.7351846243003757,
        "time": 8415.753296375275
      },
      {
        "step": 74,
        "pool": 9,
        "train_sigma": 0.007484585766130205,
        "test_sigma": 0.01542355822565878,
        "gap": 2.0607096648494023,
        "time": 8528.683575868607
      },
      {
        "step": 75,
        "pool": 9,
        "train_sigma": 0.006625367134874191,
        "test_sigma": 0.01553245999534158,
        "gap": 2.3443923452306206,
        "time": 8641.42255783081
      },
      {
        "step": 76,
        "pool": 9,
        "train_sigma": 0.0059106489351361795,
        "test_sigma": 0.015634545285731247,
        "gap": 2.6451486896457053,
        "time": 8754.03786611557
      },
      {
        "step": 77,
        "pool": 9,
        "train_sigma": 0.005385320774324093,
        "test_sigma": 0.0156265385116446,
        "gap": 2.901691313570058,
        "time": 8867.936541080475
      },
      {
        "step": 78,
        "pool": 9,
        "train_sigma": 0.004943439208086337,
        "test_sigma": 0.01595951719197714,
        "gap": 3.22842388066005,
        "time": 8981.845692873001
      },
      {
        "step": 79,
        "pool": 9,
        "train_sigma": 0.004560450255968779,
        "test_sigma": 0.01627463087815927,
        "gap": 3.5686456302990726,
        "time": 9096.026572227478
      }
    ]
  }
}